LICENSE
README.md
setup.py
ixcpy/__init__.py
ixcpy/connection.py
ixcpy/environment.py
ixcpy/query.py
ixcpy/response.py
ixcpy/status.py
ixcpy.egg-info/PKG-INFO
ixcpy.egg-info/SOURCES.txt
ixcpy.egg-info/dependency_links.txt
ixcpy.egg-info/requires.txt
ixcpy.egg-info/top_level.txt