Metadata-Version: 2.4
Name: ixcpy
Version: 2.0.0
Summary: Wrapper não oficial para conexão com a API do sistema IXC Provedor
Home-page: https://github.com/SousaFelipe/ixcpy
Author: Felipe Sousa
Author-email: fscarmo@proton.me
License: MIT License
Keywords: ixc,ixcsoft,api ixc,ixc provedor,ixc python
License-File: LICENSE
Requires-Dist: requests
Dynamic: author
Dynamic: author-email
Dynamic: description
Dynamic: description-content-type
Dynamic: home-page
Dynamic: keywords
Dynamic: license
Dynamic: license-file
Dynamic: requires-dist
Dynamic: summary
